brolog/__init__.py
brolog/cli.py
brolog/lex.py
brolog/objects.py
brolog/parse.py
brolog/solver.py
brolog-0.1.0.dist-info/LICENSE
brolog-0.1.0.dist-info/METADATA
brolog-0.1.0.dist-info/WHEEL
brolog-0.1.0.dist-info/entry_points.txt
brolog-0.1.0.dist-info/top_level.txt
brolog-0.1.0.dist-info/RECORD
