Metadata-Version: 2.1
Name: brolog
Version: 0.1.0
Summary: Prolog interpreter written in Python
Author: Tomas R.
License: MIT License
Project-URL: Homepage, https://github.com/tomasr8/brolog
Project-URL: Github, https://github.com/tomasr8/brolog
Keywords: QR,QR code,Image processing,Augmented reality,Computer vision,opencv
Classifier: Development Status :: 4 - Beta
Classifier: Intended Audience :: Developers
Classifier: Intended Audience :: Education
Classifier: Intended Audience :: Science/Research
Classifier: License :: OSI Approved :: MIT License
Classifier: Natural Language :: English
Classifier: Operating System :: OS Independent
Classifier: Programming Language :: Python
Classifier: Programming Language :: Python :: 3
Classifier: Programming Language :: Python :: Implementation :: CPython
Classifier: Topic :: Education
Classifier: Topic :: Scientific/Engineering
Classifier: Topic :: Software Development :: Interpreters
Requires-Python: >=3.11
License-File: LICENSE
Requires-Dist: click
Provides-Extra: dev
Requires-Dist: pytest ; extra == 'dev'
Requires-Dist: pytest-snapshot ; extra == 'dev'
Requires-Dist: pre-commit ; extra == 'dev'
Requires-Dist: ruff ; extra == 'dev'
